netconflib/__init__.py
netconflib/__main__.py
netconflib/client.py
netconflib/commands.py
netconflib/constants.py
netconflib/gui.py
netconflib/helper.py
netconflib/netconf.py
netconflib/server.py
netconflib/sniffer.py
netconflib/ssh.py
netconflib-1.0.6.dist-info/DESCRIPTION.rst
netconflib-1.0.6.dist-info/METADATA
netconflib-1.0.6.dist-info/RECORD
netconflib-1.0.6.dist-info/WHEEL
netconflib-1.0.6.dist-info/entry_points.txt
netconflib-1.0.6.dist-info/metadata.json
netconflib-1.0.6.dist-info/top_level.txt
