Metadata-Version: 2.0
Name: netconflib
Version: 1.0.6
Summary: A network topology configurator library
Home-page: https://github.com/XHotSniperX/Netconflib
Author: Akan Yilmaz
Author-email: captain_akan_91@hotmail.com
License: UNKNOWN
Requires-Dist: treelib
Requires-Dist: paramiko
Requires-Dist: scapy (>=2.4.0rc4)
Requires-Dist: appjar (==0.91)
